xml_dataclasses/__init__.py
xml_dataclasses/exceptions.py
xml_dataclasses/lxml_utils.py
xml_dataclasses/modifiers.py
xml_dataclasses/options.py
xml_dataclasses/py.typed
xml_dataclasses/resolve_types.py
xml_dataclasses/serde.py
xml_dataclasses-0.0.9.dist-info/LICENSE
xml_dataclasses-0.0.9.dist-info/WHEEL
xml_dataclasses-0.0.9.dist-info/METADATA
xml_dataclasses-0.0.9.dist-info/RECORD
