Metadata-Version: 2.1
Name: xml-dataclasses
Version: 0.0.9
Summary: (De)serialize XML documents into specially-annotated dataclasses
Home-page: https://github.com/tobywf/xml_dataclasses
License: MPL-2.0
Author: Toby Fleming
Author-email: tobywf@users.noreply.github.com
Requires-Python: >=3.7,<4.0
Classifier: Development Status :: 3 - Alpha
Classifier: Intended Audience :: Developers
Classifier: License :: OSI Approved
Classifier: Natural Language :: English
Classifier: Operating System :: OS Independent
Classifier: Programming Language :: Python :: 3
Classifier: Programming Language :: Python :: 3 :: Only
Classifier: Programming Language :: Python :: 3.10
Classifier: Programming Language :: Python :: 3.7
Classifier: Programming Language :: Python :: 3.8
Classifier: Programming Language :: Python :: 3.9
Classifier: Topic :: Text Processing :: Markup :: XML
Requires-Dist: lxml (>=4.6.3,<5.0.0)
